core_ciphers/__init__.py
core_ciphers/aes_cipher.py
core_ciphers/base.py
core_ciphers/py.typed
core_ciphers-1.2.1.dist-info/licenses/LICENSE
core_ciphers-1.2.1.dist-info/METADATA
core_ciphers-1.2.1.dist-info/WHEEL
core_ciphers-1.2.1.dist-info/top_level.txt
core_ciphers-1.2.1.dist-info/RECORD
